odoo/addons/sale_planned_consumed_date/README.rst
odoo/addons/sale_planned_consumed_date/__init__.py
odoo/addons/sale_planned_consumed_date/__manifest__.py
odoo/addons/sale_planned_consumed_date/i18n/fr.po
odoo/addons/sale_planned_consumed_date/i18n/it.po
odoo/addons/sale_planned_consumed_date/i18n/sale_planned_consumed_date.pot
odoo/addons/sale_planned_consumed_date/models/__init__.py
odoo/addons/sale_planned_consumed_date/models/sale_order_line.py
odoo/addons/sale_planned_consumed_date/readme/CONTRIBUTORS.md
odoo/addons/sale_planned_consumed_date/readme/DESCRIPTION.md
odoo/addons/sale_planned_consumed_date/static/description/icon.png
odoo/addons/sale_planned_consumed_date/static/description/index.html
odoo/addons/sale_planned_consumed_date/tests/__init__.py
odoo/addons/sale_planned_consumed_date/tests/test_sale_planned_consumed_date.py
odoo_addon_sale_planned_consumed_date-17.0.1.0.0.4.dist-info/METADATA
odoo_addon_sale_planned_consumed_date-17.0.1.0.0.4.dist-info/WHEEL
odoo_addon_sale_planned_consumed_date-17.0.1.0.0.4.dist-info/top_level.txt
odoo_addon_sale_planned_consumed_date-17.0.1.0.0.4.dist-info/RECORD
